{
  "type": "tabs",
  "i18n": true,
  "items": {
    "tab_settings": {
      "type": "panel",
      "label": "Einstellungen",
      "items": {
        "city": {
          "type": "text",
          "label": "Ort",
          "help": "z.B. Dettingen unter Teck",
          "sm": 12,
          "md": 6
        },
        "street": {
          "type": "text",
          "label": "Straße",
          "help": "z.B. Am Kelterplatz",
          "sm": 12,
          "md": 6
        },
        "updateInterval": {
          "type": "number",
          "label": "Aktualisierung (Stunden)",
          "min": 1,
          "max": 24,
          "default": 6,
          "sm": 12,
          "md": 4
        }
      }
    },
    "tab_wastetypes": {
      "type": "panel",
      "label": "Abfalltypen",
      "items": {
        "wasteTypes": {
          "type": "table",
          "label": "Abfalltypen",
          "items": {
            "name": {
              "type": "text",
              "label": "Name",
              "width": "20%"
            },
            "id": {
              "type": "text",
              "label": "ID",
              "width": "20%"
            },
            "keywords": {
              "type": "text",
              "label": "Schlüsselwörter (kommagetrennt)",
              "width": "50%"
            },
            "color": {
              "type": "color",
              "label": "Farbe",
              "width": "10%"
            }
          },
          "default": [
            {
              "name": "Restmüll",
              "id": "restmuell",
              "keywords": "Restmüll,Restabfall,Graue Tonne",
              "color": "#808080"
            },
            {
              "name": "Biomüll",
              "id": "biomuell",
              "keywords": "Biomüll,Biotonne,Braune Tonne,Bio",
              "color": "#8B4513"
            },
            {
              "name": "Papier",
              "id": "papier",
              "keywords": "Papier,Papiertonne,Blaue Tonne",
              "color": "#0000FF"
            },
            {
              "name": "Gelber Sack",
              "id": "gelberSack",
              "keywords": "Gelber Sack,Gelbe Tonne,Leichtverpackung,LVP",
              "color": "#FFD700"
            }
          ]
        }
      }
    }
  }
}
